topsis/__init__.py
topsis/__main__.py
topsis/pro.py
Topsis_Agamjot_102016068-1.0.1.dist-info/LICENSE
Topsis_Agamjot_102016068-1.0.1.dist-info/METADATA
Topsis_Agamjot_102016068-1.0.1.dist-info/WHEEL
Topsis_Agamjot_102016068-1.0.1.dist-info/entry_points.txt
Topsis_Agamjot_102016068-1.0.1.dist-info/top_level.txt
Topsis_Agamjot_102016068-1.0.1.dist-info/RECORD
