Metadata-Version: 2.1
Name: Topsis-Agamjot-102016068
Version: 1.0.1
Summary: Topsis package for MCDM problems
Home-page: https://github.com/Agamjot12
Author: Agamjot Singh
Author-email: agamjotworks@gmail.com
License: MIT
Keywords: python,TOPSIS,MCDM,MCDA,statistics,prescriptive analytics,cli
Platform: UNKNOWN
Classifier: Development Status :: 3 - Alpha
Classifier: Intended Audience :: Developers
Classifier: Programming Language :: Python :: 3
Classifier: License :: OSI Approved :: MIT License
Classifier: Operating System :: OS Independent
Requires-Python: >=3.6
License-File: LICENSE
Requires-Dist: pandas
Requires-Dist: numpy
